swbs/__init__.py
swbs-1.2.8.dist-info/LICENSE
swbs-1.2.8.dist-info/WHEEL
swbs-1.2.8.dist-info/METADATA
swbs-1.2.8.dist-info/RECORD
