Metadata-Version: 2.1
Name: swbs
Version: 1.2.8
Summary: General-purpose socket wrapper for sending and receiving byte strings.
Home-page: https://dreamerslegacy.xyz/git/perpetualCreations/swbs
License: MIT
Author: perpetualCreations
Author-email: tchen0584@gmail.com
Requires-Python: >=3.9,<4.0
Classifier: License :: OSI Approved :: MIT License
Classifier: Programming Language :: Python :: 3
Classifier: Programming Language :: Python :: 3.10
Classifier: Programming Language :: Python :: 3.9
Requires-Dist: pycryptodomex (>=3.15.0,<4.0.0)
Project-URL: Documentation, https://dreamerslegacy.xyz/projects/swbs/docs/html/index.html
Project-URL: Repository, https://dreamerslegacy.xyz/git/perpetualCreations/swbs
